easypeasy/__init__.py
easypeasy/decorators.py
flask_ezlogin/__init__.py
flask_ezlogin/decorators.py
flask_ezlogin-0.2.1.dist-info/METADATA
flask_ezlogin-0.2.1.dist-info/WHEEL
flask_ezlogin-0.2.1.dist-info/top_level.txt
flask_ezlogin-0.2.1.dist-info/RECORD
