Metadata-Version: 2.1
Name: flask-ezlogin
Version: 0.2.1
Summary: Easy login setup with Flask and Flask-Login
Home-page: https://github.com/arturads/flask-ezlogin
Author: Artur Arantes Santos da Silva
Author-email: arturarantesads@gmail.com
Classifier: Programming Language :: Python :: 3
Classifier: Framework :: Flask
Classifier: License :: OSI Approved :: MIT License
Classifier: Operating System :: OS Independent
Requires-Python: >=3.6
Requires-Dist: Flask
Requires-Dist: Flask-Login
